IOTDevicesService/__init__.py
IOTDevicesService/__main__.py
IOTDevicesService/const.py
IOTDevicesService/service.py
pih_iot-0.141.dist-info/METADATA
pih_iot-0.141.dist-info/WHEEL
pih_iot-0.141.dist-info/entry_points.txt
pih_iot-0.141.dist-info/top_level.txt
pih_iot-0.141.dist-info/RECORD
