Metadata-Version: 2.1
Name: pih-iot
Version: 0.141
Summary: PIH IOT Devices service package
Home-page: https://pacifichosp.com/
Author: Nikita Karachentsev
Author-email: it@pacifichosp.com
License: MIT
Requires-Dist: ipih
Requires-Dist: tinytuya
